{"version":153,"duration":4287658,"pause":120342,"calories":1021,"subjective_feeling":"good","dehydration_volume":1786,"plausible":true,"start_time_timezone_offset":10800000,"end_time_timezone_offset":10800000,"tracking_method":"tracked","start_time":1564518326000,"end_time":1564522734000,"user_perceived_start_time":1564529126000,"user_perceived_end_time":1564533534000,"created_at":1564518326000,"updated_at":1717124767853,"features":[{"type":"weather","attributes":{"conditions":"night","temperature":26.0,"wind_speed":3.888888888888889,"wind_direction":0.0,"humidity":77.0}},{"type":"map","attributes":{"encoded_trace":"wv}aE{tzsEAHfE}IoIcFCcPrDgFxH_NmIqKwHsIzK|AzLxFxJpHzJ|FpJrIrFpN_GnIuIjF]yJyB}ArBJiBdBHwDMvHxAyAuCsEYzN{C~M}@pBjKG|DcLlHgLtL\\dMz@oIgAwIoIgFgMwH_JmHoHgFo@uKmGyIqDgKsG}I}GkJoAqH~JyGpKaApOxHnMrGzK`J`IrHlCpClD","trace_available":true,"start_latitude":"31.942367553710938","start_longitude":34.87582015991211}},{"type":"track_metrics","attributes":{"distance":13023,"average_speed":"3.0373224730144055","average_pace":0.3292373493050756,"max_speed":"3.8818282551235623","elevation_gain":74,"elevation_loss":72,"surface":"road"}},{"type":"fastest_segments","attributes":{"segments":[{"distance":"1km","duration":302372,"started_at":1564518546000},{"distance":"1mi","duration":491405,"started_at":1564518528000},{"distance":"3mi","duration":1537498,"started_at":1564518380000},{"distance":"5km","duration":1590398,"started_at":1564518360000},{"distance":"10km","duration":3265232,"started_at":1564518360000}]}},{"type":"heart_rate","attributes":{"average":153,"maximum":166,"trace_available":true,"zones":[{"name":"not_in_zone","distance":0,"duration":369},{"name":"easy","distance":138,"duration":55443,"minimum_heart_rate":128,"maximum_heart_rate":138},{"name":"fat_burning","distance":3213,"duration":1086843,"minimum_heart_rate":139,"maximum_heart_rate":148},{"name":"aerobic","distance":7915,"duration":2591709,"minimum_heart_rate":149,"maximum_heart_rate":159},{"name":"anaerobic","distance":1757,"duration":553294,"minimum_heart_rate":160,"maximum_heart_rate":170},{"name":"red_line","distance":0,"duration":0,"minimum_heart_rate":171,"maximum_heart_rate":255}]}},{"type":"steps","attributes":{"average_step_rate":158,"maximum_step_rate":168,"total_steps":11350,"average_step_length":114}},{"type":"initial_values","attributes":{"distance":13023,"duration":4287658,"pause":120342,"sport_type":{"id":"1","type":"sport_type"},"start_time":1564518326000,"end_time":1564522734000}},{"type":"origin","attributes":{"device":{"name":"iPhone9,3","vendor":"Apple","os_version":"iOS 12.2"}}},{"type":"groups","attributes":{"groups":[{"id":"dd77e8bc-8459-4428-a318-a33114dea6f3","type":"group"}]}}],"id":"9cc69375-4b62-4908-81a4-306256460760","user_id":"7dd9f4c8-42e2-0f38-947d-20091b85fcb9","sport_type_id":"1","creation_application_id":"2563"}