{"version":191,"duration":5385000,"pause":0,"calories":1489,"subjective_feeling":"awesome","dehydration_volume":1627,"plausible":true,"start_time_timezone_offset":7200000,"end_time_timezone_offset":7200000,"tracking_method":"tracked","start_time":1547328485000,"end_time":1547333870000,"user_perceived_start_time":1547335685000,"user_perceived_end_time":1547341070000,"created_at":1547328486000,"updated_at":1717124816368,"features":[{"type":"weather","attributes":{"conditions":"night","temperature":9.0,"wind_speed":"2.7777777777777777","wind_direction":120.0,"humidity":73.0}},{"type":"map","attributes":{"encoded_trace":"ky}aEyt{sEBKxDkKjA{SeNmMnPtErQ~I~OxJbM|OmDxQoOzBU}Ll@UjCxBkAbDc@{@s@aE\\a@nCvB_CzFaHxUtCv@bKyLpMcOlRtDgHkB{JuQkLmOwQaKaOwIoNiHgOmK_MdGuKpP?~PhKdPtM`OrMtFjCsSyHxGrEhNpHfGsDuJYqSqItF|FrNtGjHyDyJAmTmI|HhGdDZcO","trace_available":true,"start_latitude":"31.942785263061523","start_longitude":34.88093185424805}},{"type":"track_metrics","attributes":{"distance":18121,"average_speed":3.365088207985144,"average_pace":"0.29716903040671044","max_speed":4.611903826395671,"elevation_gain":85,"elevation_loss":85,"surface":"road"}},{"type":"fastest_segments","attributes":{"segments":[{"distance":"1km","duration":262824,"started_at":1547328512000},{"distance":"1mi","duration":430352,"started_at":1547328486000},{"distance":"3mi","duration":1349682,"started_at":1547328486000},{"distance":"5km","duration":1396957,"started_at":1547328512000},{"distance":"10km","duration":2828433,"started_at":1547328512000}]}},{"type":"heart_rate","attributes":{"average":166,"maximum":184,"trace_available":true,"zones":[{"name":"not_in_zone","distance":0,"duration":194},{"name":"easy","distance":0,"duration":0,"minimum_heart_rate":128,"maximum_heart_rate":138},{"name":"fat_burning","distance":474,"duration":149935,"minimum_heart_rate":139,"maximum_heart_rate":148},{"name":"aerobic","distance":2537,"duration":815198,"minimum_heart_rate":149,"maximum_heart_rate":159},{"name":"anaerobic","distance":5150,"duration":1601307,"minimum_heart_rate":160,"maximum_heart_rate":170},{"name":"red_line","distance":9960,"duration":2818366,"minimum_heart_rate":171,"maximum_heart_rate":255}]}},{"type":"steps","attributes":{"average_step_rate":163,"maximum_step_rate":179,"total_steps":14723,"average_step_length":123}},{"type":"initial_values","attributes":{"distance":18121,"duration":5385000,"pause":0,"sport_type":{"id":"1","type":"sport_type"},"start_time":1547328485000,"end_time":1547333870000}},{"type":"origin","attributes":{"device":{"name":"iPhone7,2","vendor":"Apple","os_version":"iOS 12.1.2"}}},{"type":"groups","attributes":{"groups":[{"id":"dd77e8bc-8459-4428-a318-a33114dea6f3","type":"group"}]}}],"id":"503f6b1d-8f5b-4a0d-b0b2-0cf792582866","user_id":"7dd9f4c8-42e2-0f38-947d-20091b85fcb9","sport_type_id":"1","creation_application_id":"2474"}